easywall/__init__.py
easywall/__main__.py
easywall/acceptance.py
easywall/config.py
easywall/easywall.py
easywall/iptables_handler.py
easywall/log.py
easywall/rules_handler.py
easywall/utility.py
easywall/web/__init__.py
easywall/web/__main__.py
easywall/web/apply.py
easywall/web/blacklist.py
easywall/web/custom.py
easywall/web/defaultpayload.py
easywall/web/error.py
easywall/web/firstrun.py
easywall/web/forwarding.py
easywall/web/index.py
easywall/web/login.py
easywall/web/options.py
easywall/web/passwd.py
easywall/web/ports.py
easywall/web/webutils.py
easywall/web/whitelist.py
tests/__init__.py
tests/utils.py
easywall-0.3.1.dist-info/LICENSE
easywall-0.3.1.dist-info/METADATA
easywall-0.3.1.dist-info/WHEEL
easywall-0.3.1.dist-info/top_level.txt
easywall-0.3.1.dist-info/RECORD
