Metadata-Version: 2.1
Name: easywall
Version: 0.3.1
Summary: Web interface for easy use of the IPTables firewall on Linux systems written in Python3
Home-page: https://github.com/jpylypiw/easywall
Author: Jochen Pylypiw
Author-email: 12394156+jpylypiw@users.noreply.github.com
License: GPL-3.0
Project-URL: Bug Tracker, https://github.com/jpylypiw/easywall/issues
Project-URL: Documentation, https://github.com/jpylypiw/easywall/blob/master/README.md
Project-URL: Source Code, https://github.com/jpylypiw/easywall
Keywords: firewall,iptables,linux,framework,easywall
Platform: UNKNOWN
Classifier: Framework :: Flask
Classifier: Topic :: System :: Networking :: Firewalls
Classifier: Development Status :: 4 - Beta
Classifier: License :: OSI Approved :: GNU General Public License v3 or later (GPLv3+)
Classifier: Programming Language :: Unix Shell
Classifier: Programming Language :: Python :: 3.6
Classifier: Programming Language :: Python :: 3.7
Classifier: Programming Language :: Python :: 3.8
Classifier: Programming Language :: Python :: 3.9
Classifier: Programming Language :: Python :: Implementation :: CPython
Classifier: Operating System :: POSIX :: Linux
Classifier: Operating System :: Unix
Classifier: Intended Audience :: Developers
Classifier: Intended Audience :: System Administrators
Classifier: Natural Language :: English
Requires-Python: >=3.6
Requires-Dist: watchdog
Requires-Dist: Flask
Requires-Dist: natsort
Requires-Dist: flask-ipban
Requires-Dist: pyyaml
